imgtk/__init__.py
imgtk/_version.py
imgtk/cli.py
imgtk/deduplicate/__init__.py
imgtk/deduplicate/deduplicate.py
imgtk/exifsort/__init__.py
imgtk/exifsort/exifsort.py
imgtk/i2p/__init__.py
imgtk/i2p/i2p.py
imgtk-1.2.0.dist-info/licenses/LICENSE
imgtk-1.2.0.dist-info/METADATA
imgtk-1.2.0.dist-info/WHEEL
imgtk-1.2.0.dist-info/entry_points.txt
imgtk-1.2.0.dist-info/top_level.txt
imgtk-1.2.0.dist-info/RECORD
