Metadata-Version: 2.4
Name: imgtk
Version: 1.2.0
Summary: Image file manipulation toolkit
Author-email: koma <okunoya@path-works.net>
License: LICENSE
Project-URL: homepage, https://github.com/koma75/imgtk
Project-URL: documentation, https://github.com/koma75/imgtk/blob/main/README.md
Project-URL: repository, https://github.com/koma75/imgtk.git
Classifier: Development Status :: 5 - Production/Stable
Classifier: Environment :: Console
Classifier: Intended Audience :: End Users/Desktop
Classifier: License :: OSI Approved :: BSD License
Classifier: Natural Language :: English
Classifier: Operating System :: MacOS :: MacOS X
Classifier: Operating System :: Microsoft :: Windows :: Windows 10
Classifier: Operating System :: POSIX :: Linux
Classifier: Programming Language :: Python :: 3
Classifier: Programming Language :: Python :: 3.9
Classifier: Topic :: Utilities
Requires-Python: >=3.9
License-File: LICENSE
Requires-Dist: click<9,>=8.1
Requires-Dist: PyYaml<7,>=6
Requires-Dist: pillow<12,>=11.3
Requires-Dist: imagehash<5,>=4.3
Requires-Dist: fpdf2<3,>=2.6
Requires-Dist: tqdm<5,>=4.67
Provides-Extra: dev
Requires-Dist: pyinstaller; extra == "dev"
Requires-Dist: build; extra == "dev"
Requires-Dist: twine; extra == "dev"
Dynamic: license-file
